LICENSE
MANIFEST.in
README.md
setup.cfg
setup.py
iopipe/__init__.py
iopipe/agent.py
iopipe/collector.py
iopipe/compat.py
iopipe/config.py
iopipe/constants.py
iopipe/context.py
iopipe/handler.py
iopipe/iopipe.py
iopipe/mock_system.py
iopipe/monotonic.py
iopipe/plugins.py
iopipe/report.py
iopipe/send_report.py
iopipe/signer.py
iopipe/system.py
iopipe/timeout.py
iopipe.egg-info/PKG-INFO
iopipe.egg-info/SOURCES.txt
iopipe.egg-info/dependency_links.txt
iopipe.egg-info/requires.txt
iopipe.egg-info/top_level.txt
iopipe.egg-info/zip-safe
iopipe/contrib/__init__.py
iopipe/contrib/eventinfo/__init__.py
iopipe/contrib/eventinfo/event_types.py
iopipe/contrib/eventinfo/plugin.py
iopipe/contrib/eventinfo/response_types.py
iopipe/contrib/eventinfo/util.py
iopipe/contrib/logger/__init__.py
iopipe/contrib/logger/formatter.py
iopipe/contrib/logger/plugin.py
iopipe/contrib/logger/request.py
iopipe/contrib/logger/stream.py
iopipe/contrib/logger/wrapper.py
iopipe/contrib/profiler/__init__.py
iopipe/contrib/profiler/plugin.py
iopipe/contrib/profiler/request.py
iopipe/contrib/trace/__init__.py
iopipe/contrib/trace/auto_db.py
iopipe/contrib/trace/auto_http.py
iopipe/contrib/trace/dbapi.py
iopipe/contrib/trace/marker.py
iopipe/contrib/trace/plugin.py
iopipe/contrib/trace/timeline.py
iopipe/contrib/trace/util.py