Metadata-Version: 2.1
Name: iopipe
Version: 1.10.1
Summary: IOpipe agent for serverless Application Performance Monitoring
Home-page: https://github.com/iopipe/iopipe-python
Author: IOpipe
Author-email: dev@iopipe.com
License: UNKNOWN
Platform: UNKNOWN
Classifier: Development Status :: 5 - Production/Stable
Classifier: Intended Audience :: Developers
Classifier: License :: OSI Approved :: Apache Software License
Classifier: Natural Language :: English
Classifier: Programming Language :: Python
Classifier: Programming Language :: Python :: 2
Classifier: Programming Language :: Python :: 2.7
Classifier: Programming Language :: Python :: 3
Classifier: Programming Language :: Python :: 3.6
Classifier: Programming Language :: Python :: 3.7
Classifier: Topic :: Internet :: WWW/HTTP
Classifier: Topic :: Internet :: WWW/HTTP :: Dynamic Content
Provides-Extra: local
Provides-Extra: coverage
Provides-Extra: dev
